HISTORY.rst
LICENSE.rst
MANIFEST.in
Makefile
README.rst
setup.py
bin/lexor
docs/Makefile
docs/source/conf.py
docs/source/index.rst
docs/source/installation.rst
docs/source/lexor.rst
docs/source/start.rst
docs/source/api/index.rst
docs/source/api/lexor.command.config.rst
docs/source/api/lexor.command.defaults.rst
docs/source/api/lexor.command.develop.rst
docs/source/api/lexor.command.dist.rst
docs/source/api/lexor.command.document.rst
docs/source/api/lexor.command.edit.rst
docs/source/api/lexor.command.install.rst
docs/source/api/lexor.command.lang.rst
docs/source/api/lexor.command.paste.rst
docs/source/api/lexor.command.rst
docs/source/api/lexor.command.test.rst
docs/source/api/lexor.command.to.rst
docs/source/api/lexor.core.converter.rst
docs/source/api/lexor.core.elements.rst
docs/source/api/lexor.core.node.rst
docs/source/api/lexor.core.parser.rst
docs/source/api/lexor.core.rst
docs/source/api/lexor.core.selector.rst
docs/source/api/lexor.core.writer.rst
docs/source/api/lexor.rst
docs/source/commands/config.rst
docs/source/commands/index.rst
docs/source/commands/install.rst
docs/source/topics/environ.rst
docs/source/topics/index.rst
lexor/__init__.py
lexor/__main__.py
lexor/__version__.py
lexor.egg-info/PKG-INFO
lexor.egg-info/SOURCES.txt
lexor.egg-info/dependency_links.txt
lexor.egg-info/pbr.json
lexor.egg-info/requires.txt
lexor.egg-info/top_level.txt
lexor/command/__init__.py
lexor/command/cloud.py
lexor/command/config.py
lexor/command/defaults.py
lexor/command/develop.py
lexor/command/dist.py
lexor/command/document.py
lexor/command/inspect.py
lexor/command/install.py
lexor/command/lang.py
lexor/command/paste.py
lexor/command/test.py
lexor/command/to.py
lexor/core/__init__.py
lexor/core/converter.py
lexor/core/elements.py
lexor/core/node.py
lexor/core/parser.py
lexor/core/selector.py
lexor/core/writer.py
lexor/core/zig.py
lexor/core/templates/converter-style.txt
lexor/core/templates/node-converter-test.txt
lexor/core/templates/node-converter.txt
lexor/core/templates/node-parser-test.txt
lexor/core/templates/node-parser.txt
lexor/core/templates/node-writer-test.txt
lexor/core/templates/node-writer.txt
