Metadata-Version: 1.1
Name: lexor
Version: 0.1.5rc0
Summary: Document converter implemented in python.
Home-page: http://lexor.readthedocs.org
Author: Manuel Lopez
Author-email: jmlopez.rod@gmail.com
License: BSD License
Keywords: lexor markdown html
Platform: UNKNOWN
Classifier: Development Status :: 4 - Beta
Classifier: License :: OSI Approved :: BSD License
Classifier: Operating System :: MacOS :: MacOS X
Classifier: Operating System :: POSIX :: Linux
Classifier: Programming Language :: Python
Classifier: Programming Language :: Python :: 2.7
Classifier: Topic :: Documentation
Classifier: Topic :: Communications :: Email
Classifier: Topic :: Text Processing
Classifier: Topic :: Text Processing :: Linguistic
Classifier: Topic :: Text Processing :: Markup
